REL/__init__.py
REL/entity_disambiguation.py
REL/generate_train_test.py
REL/mention_detection.py
REL/mention_detection_base.py
REL/mulrel_ranker.py
REL/server.py
REL/training_datasets.py
REL/utils.py
REL/vocabulary.py
REL/wikipedia.py
REL/wikipedia_yago_freq.py
REL/db/__init__.py
REL/db/base.py
REL/db/generic.py
REL/models/__init__.py
REL/models/models.json
REL/ner/__init__.py
REL/ner/base.py
REL/ner/flair_wrapper.py
REL/ner/ngram.py
radboud_el-0.0.1.dist-info/LICENSE
radboud_el-0.0.1.dist-info/METADATA
radboud_el-0.0.1.dist-info/WHEEL
radboud_el-0.0.1.dist-info/top_level.txt
radboud_el-0.0.1.dist-info/RECORD
