Metadata-Version: 2.1
Name: radboud-el
Version: 0.0.1
Summary: REL: Radboud Entity Linker
Home-page: https://github.com/informagi/REL
Author: Johannes Michael
Author-email: mick.vanhulst@gmail.com
Project-URL: Bug Tracker, https://github.com/informagi/REL/issues
Project-URL: Documentation, https://rel.readthedocs.io
Keywords: entity-linking,entity-disambiguation,wikipedia,natural-language-processing
Classifier: Development Status :: 4 - Beta
Classifier: Intended Audience :: Developers
Classifier: Intended Audience :: Science/Research
Classifier: License :: OSI Approved :: MIT License
Classifier: Natural Language :: English
Classifier: Operating System :: OS Independent
Classifier: Programming Language :: Python :: 3
Classifier: Programming Language :: Python :: 3.7
Classifier: Programming Language :: Python :: 3.8
Classifier: Programming Language :: Python :: 3.9
Classifier: Programming Language :: Python :: 3.10
Classifier: Programming Language :: Python :: 3.11
Classifier: Topic :: Scientific/Engineering
License-File: LICENSE
Requires-Dist: colorama
Requires-Dist: konoha
Requires-Dist: flair (>=0.11)
Requires-Dist: segtok
Requires-Dist: torch
Requires-Dist: nltk
Requires-Dist: anyascii
Provides-Extra: develop
Requires-Dist: bump2version ; extra == 'develop'
Requires-Dist: black ; extra == 'develop'
Requires-Dist: coverage ; extra == 'develop'
Requires-Dist: flake8 ; extra == 'develop'
Requires-Dist: isort ; extra == 'develop'
Requires-Dist: pytest ; extra == 'develop'
Provides-Extra: docs
Requires-Dist: markdown-include ; extra == 'docs'
Requires-Dist: mkdocs ; extra == 'docs'
Requires-Dist: mkdocs-material ; extra == 'docs'
Requires-Dist: mkdocstrings[python] ; extra == 'docs'
Provides-Extra: publishing
Requires-Dist: twine ; extra == 'publishing'
Requires-Dist: wheel ; extra == 'publishing'
Requires-Dist: build ; extra == 'publishing'
